bester_logger/__init__.py
bester_logger/main.py
bester_logger-0.0.8.dist-info/METADATA
bester_logger-0.0.8.dist-info/WHEEL
bester_logger-0.0.8.dist-info/licenses/LICENSE
bester_logger-0.0.8.dist-info/RECORD
