Metadata-Version: 2.4
Name: bester-logger
Version: 0.0.8
Summary: A easier way to log data to database or files when building applications fast.
Project-URL: Homepage, https://github.com/REHXZ/Better_Logger
Project-URL: Issues, https://github.com/REHXZ/Better_Logger/issues
Author-email: Rejey Ezekiel Jeyakumar <rehxxz@gmail.com>
License-Expression: MIT
License-File: LICENSE
Classifier: Operating System :: OS Independent
Classifier: Programming Language :: Python :: 3
Requires-Python: >=3.9
Requires-Dist: pyodbc>=5.2
